covid19_morocco/covid19.py
covid19_morocco/test.py
covid19_morocco-0.0.2.dist-info/METADATA
covid19_morocco-0.0.2.dist-info/WHEEL
covid19_morocco-0.0.2.dist-info/top_level.txt
covid19_morocco-0.0.2.dist-info/RECORD
