Metadata-Version: 2.1
Name: covid19-morocco
Version: 0.0.2
Summary: A Python Package to get covid19 Cases for Morocco in Real Time
Home-page: https://github.com/Mohamedballouch/
Author: Ballouch
Author-email: mohamedballouch10@gmail.com
License: UNKNOWN
Platform: UNKNOWN
Classifier: Programming Language :: Python :: 3
Classifier: Programming Language :: Python :: 3.5
Classifier: Programming Language :: Python :: 3.6
Classifier: Programming Language :: Python :: 3.7
Classifier: Programming Language :: Python :: 3.8
Classifier: License :: OSI Approved :: MIT License
Classifier: Operating System :: OS Independent
Requires-Python: >=3.6
